Metadata-Version: 2.4
Name: opttx
Version: 0.1.0a1
Summary: JAX/Flax/Optax optimizer manager
Author: Tianshi Xu
License: MIT License
Project-URL: Homepage, https://github.com/Hitenze/opttx
Project-URL: Repository, https://github.com/Hitenze/opttx
Project-URL: Issues, https://github.com/Hitenze/opttx/issues
Keywords: jax,optax,flax,optimizer
Classifier: Development Status :: 3 - Alpha
Classifier: Programming Language :: Python :: 3
Classifier: License :: OSI Approved :: MIT License
Classifier: Operating System :: OS Independent
Classifier: Intended Audience :: Science/Research
Classifier: Topic :: Scientific/Engineering :: Artificial Intelligence
Requires-Python: >=3.10
License-File: LICENSE
Requires-Dist: jax>=0.4.20
Requires-Dist: jaxlib>=0.4.20
Requires-Dist: optax>=0.2.0
Requires-Dist: flax>=0.8.0
Provides-Extra: dev
Requires-Dist: pytest>=7.4; extra == "dev"
Dynamic: license-file
